{"_ts":[1558862237,1558957986],"_r":{"breakdown":{"html":{"bytes":[5291,7143],"requests":[5,5]},"js":{"bytes":[233584,231363],"requests":[8,8]},"css":{"bytes":[39074,39074],"requests":[6,6]},"image":{"bytes":[774631,751231],"requests":[9,9]},"flash":{"bytes":[0,0],"requests":[0,0]},"font":{"bytes":[122912,122912],"requests":[2,2]},"video":{"bytes":[0,0],"requests":[0,0]},"other":{"bytes":[0,0],"requests":[0,1]}},"date":[1558862237,1558957986],"domElements":[201,202],"domInteractive":[3212,3398],"firstPaint":[1309.7750000002,1414.215],"fullyLoaded":[3657,3861],"id":["190525_QM_ad78fed32328e27b349a0d2e7070f792","190526_SM_1fa381a7b91a32d95336b0b90e2014ee"],"loadTime":[3479,3668],"render":[1400,1500],"SpeedIndex":[2414,2749],"TTFB":[341,370],"videoFrames":[[{"_i":"ms_000000.jpg","_t":0,"_vc":0},{"_i":"ms_001400.jpg","_t":1400,"_vc":6},{"_i":"ms_001700.jpg","_t":1700,"_vc":6},{"_i":"ms_001800.jpg","_t":1800,"_vc":6},{"_i":"ms_001900.jpg","_t":1900,"_vc":6},{"_i":"ms_002300.jpg","_t":2300,"_vc":71},{"_i":"ms_002500.jpg","_t":2500,"_vc":71},{"_i":"ms_002800.jpg","_t":2800,"_vc":98},{"_i":"ms_003600.jpg","_t":3600,"_vc":98},{"_i":"ms_003900.jpg","_t":3900,"_vc":99},{"_i":"ms_004000.jpg","_t":4000,"_vc":100}],[{"_i":"ms_000000.jpg","_t":0,"_vc":0},{"_i":"ms_001500.jpg","_t":1500,"_vc":6},{"_i":"ms_001600.jpg","_t":1600,"_vc":6},{"_i":"ms_002700.jpg","_t":2700,"_vc":6},{"_i":"ms_002800.jpg","_t":2800,"_vc":98},{"_i":"ms_002900.jpg","_t":2900,"_vc":98},{"_i":"ms_003200.jpg","_t":3200,"_vc":98},{"_i":"ms_003500.jpg","_t":3500,"_vc":98},{"_i":"ms_003800.jpg","_t":3800,"_vc":98},{"_i":"ms_004100.jpg","_t":4100,"_vc":99},{"_i":"ms_004200.jpg","_t":4200,"_vc":100}]],"visualComplete":[4000,4200],"lighthouse":[52,52],"pagespeed":[84,84]}}